planet_terp/__init__.py
planet_terp/client.py
planet_terp/models.py
planet_terp/py.typed
planet_terp_client-0.1.6.dist-info/METADATA
planet_terp_client-0.1.6.dist-info/WHEEL
planet_terp_client-0.1.6.dist-info/licenses/LICENSE
planet_terp_client-0.1.6.dist-info/RECORD
