Metadata-Version: 2.4
Name: planet-terp-client
Version: 0.1.6
Summary: a python client for the planet terp api
Project-URL: Homepage, https://github.com/ynbh/planet-terp-client
Project-URL: Repository, https://github.com/ynbh/planet-terp-client
Project-URL: Issues, https://github.com/ynbh/planet-terp-client/issues
Author-email: Yashas Bhat <ybhat@umd.edu>
License: MIT License
License-File: LICENSE
Requires-Python: >=3.9
Requires-Dist: requests
